{"_type":"export","__export_format":4,"__export_date":"2023-12-01T11:21:14.571Z","__export_source":"insomnia.desktop.app:v8.4.5","resources":[{"_id":"req_39dac6efde694dafa861a5f1d8d1f75b","parentId":"wrk_e703ff469f4642b2a84f934941732103","modified":1701429422967,"created":1701429411331,"url":"{{ _.host }}/log","name":"Log","description":"","method":"GET","body":{},"parameters":[],"headers":[{"name":"User-Agent","value":"insomnia/8.4.5"}],"authentication":{},"metaSortKey":-1701429411331,"isPrivate":false,"settingStoreCookies":true,"settingSendCookies":true,"settingDisableRenderRequestBody":false,"settingEncodeUrl":true,"settingRebuildPath":true,"settingFollowRedirects":"global","_type":"request"},{"_id":"wrk_e703ff469f4642b2a84f934941732103","parentId":null,"modified":1701429661935,"created":1701425758716,"name":"Trabalho 3","description":"","scope":"collection","_type":"workspace"},{"_id":"req_4f3a3e5b84874b6a96c5352f4d310d05","parentId":"fld_7f206a70e7864084b376653b6504a69e","modified":1701429645433,"created":1701428792811,"url":"{{ _.host }}/pecas/4/1000","name":"Peça","description":"","method":"PATCH","body":{},"parameters":[],"headers":[{"name":"User-Agent","value":"insomnia/8.4.5","id":"pair_703957a3204348be91840a0d7ad090d7"},{"id":"pair_ff973620d25342bf8b82f52ab562ab17","name":"Authorization","value":"{{ _.token }}","description":""}],"authentication":{},"metaSortKey":-1701428792811,"isPrivate":false,"settingStoreCookies":true,"settingSendCookies":true,"settingDisableRenderRequestBody":false,"settingEncodeUrl":true,"settingRebuildPath":true,"settingFollowRedirects":"global","_type":"request"},{"_id":"fld_7f206a70e7864084b376653b6504a69e","parentId":"wrk_e703ff469f4642b2a84f934941732103","modified":1701428088674,"created":1701428088674,"name":"Peãs","description":"","environment":{},"environmentPropertyOrder":null,"metaSortKey":-1701428088674,"_type":"request_group"},{"_id":"req_b8c483c3eb0f442189bd75488d9f006b","parentId":"fld_7f206a70e7864084b376653b6504a69e","modified":1701428677264,"created":1701428677264,"url":"{{ _.host }}/pecas/1","name":"Peça","description":"","method":"DELETE","body":{},"parameters":[],"headers":[{"name":"User-Agent","value":"insomnia/8.4.5","id":"pair_202c3bbb5371469e9a4b5b78f7ec1699"},{"id":"pair_3cca768d51c94721803aeb7ab788593b","name":"Authorization","value":"{{ _.token }}","description":""}],"authentication":{},"metaSortKey":-1701428376464.5,"isPrivate":false,"settingStoreCookies":true,"settingSendCookies":true,"settingDisableRenderRequestBody":false,"settingEncodeUrl":true,"settingRebuildPath":true,"settingFollowRedirects":"global","_type":"request"},{"_id":"req_36776e7bf33748dcb267488bcdaa7213","parentId":"fld_7f206a70e7864084b376653b6504a69e","modified":1701428765196,"created":1701428190653,"url":"{{ _.host }}/pecas","name":"Peça","description":"","method":"POST","body":{"mimeType":"application/json","text":"{\n\t\"nome\": \"Placa\",\n  \"preco\": 2299,\n  \"usuario_id\": 1\n}"},"parameters":[],"headers":[{"name":"Content-Type","value":"application/json","id":"pair_23ad6ad8fa764e86ab69ae309b6e1076"},{"name":"User-Agent","value":"insomnia/8.4.5","id":"pair_5f4816d0060b410eb9d2ce7f0d0558e0"},{"id":"pair_376d4c885ab244d1a7cffaee77f21efc","name":"Authorization","value":"{{ _.token }}","description":""}],"authentication":{},"metaSortKey":-1701428190653,"isPrivate":false,"settingStoreCookies":true,"settingSendCookies":true,"settingDisableRenderRequestBody":false,"settingEncodeUrl":true,"settingRebuildPath":true,"settingFollowRedirects":"global","_type":"request"},{"_id":"req_a79e28abeb9549caac2abfc2c60f15ff","parentId":"fld_7f206a70e7864084b376653b6504a69e","modified":1701428801678,"created":1701428090835,"url":"{{ _.host }}/pecas","name":"Peca","description":"","method":"GET","body":{},"parameters":[],"headers":[{"name":"User-Agent","value":"insomnia/8.4.5","id":"pair_efe1c02fedfc49db86e2b25e9baa9c96"},{"id":"pair_1787f19dd05a4b2cae4ae009ed215a36","name":"Authorization","value":"{{ _.token }}","description":""}],"authentication":{},"metaSortKey":-1701428090835,"isPrivate":false,"settingStoreCookies":true,"settingSendCookies":true,"settingDisableRenderRequestBody":false,"settingEncodeUrl":true,"settingRebuildPath":true,"settingFollowRedirects":"global","_type":"request"},{"_id":"req_fb82db62de5147c08053d8c185686652","parentId":"wrk_e703ff469f4642b2a84f934941732103","modified":1701429309514,"created":1701427202925,"url":"{{ _.host }}/usuario/novasenha/12641100da194373ace194c7966c7cc8","name":"Nova Senha","description":"","method":"PATCH","body":{"mimeType":"application/json","text":"{\n\t\"email\": \"glad@email.com\",\n\t\"novasenha\": \"!Vinicius123\"\n}"},"parameters":[],"headers":[{"name":"Content-Type","value":"application/json"},{"name":"User-Agent","value":"insomnia/8.4.5"}],"authentication":{},"metaSortKey":-1701427202925,"isPrivate":false,"settingStoreCookies":true,"settingSendCookies":true,"settingDisableRenderRequestBody":false,"settingEncodeUrl":true,"settingRebuildPath":true,"settingFollowRedirects":"global","_type":"request"},{"_id":"req_26da10f9d7734ea985a33f1f6da06790","parentId":"wrk_e703ff469f4642b2a84f934941732103","modified":1701429159804,"created":1701427059926,"url":"{{ _.host }}/usuario/trocasenha/","name":"Troca email","description":"","method":"POST","body":{"mimeType":"application/json","text":"{\n\t\"email\": \"glad@email.com\"\n}"},"parameters":[],"headers":[{"name":"Content-Type","value":"application/json"},{"name":"User-Agent","value":"insomnia/8.4.5"}],"authentication":{},"metaSortKey":-1701427059926,"isPrivate":false,"settingStoreCookies":true,"settingSendCookies":true,"settingDisableRenderRequestBody":false,"settingEncodeUrl":true,"settingRebuildPath":true,"settingFollowRedirects":"global","_type":"request"},{"_id":"req_6a7cd004137b438bab89bb1466f3c1fa","parentId":"wrk_e703ff469f4642b2a84f934941732103","modified":1701429149378,"created":1701425871290,"url":"{{ _.host }}/usuario","name":"Usuario","description":"","method":"POST","body":{"mimeType":"application/json","text":"{\n\t\"nome\": \"Gladmir\",\n\t\"email\": \"glad@email.com\",\n\t\"senha\": \"!#Vinicius123\"\n}"},"parameters":[],"headers":[{"name":"Content-Type","value":"application/json","id":"pair_14099fcebc99415aa4a66ed0fe291dfd"},{"name":"User-Agent","value":"insomnia/8.4.5","id":"pair_dd0d48a072ea4a5bb2a94f3988ce01b0"},{"id":"pair_01092d88603b45c08a9dd7bf8e2b5c0e","name":"Authorization","value":"{{ _.token }}","description":""}],"authentication":{},"metaSortKey":-1701425871290,"isPrivate":false,"settingStoreCookies":true,"settingSendCookies":true,"settingDisableRenderRequestBody":false,"settingEncodeUrl":true,"settingRebuildPath":true,"settingFollowRedirects":"global","_type":"request"},{"_id":"req_ef9ce22b6bdc447aa3d7ec5929be27a9","parentId":"wrk_e703ff469f4642b2a84f934941732103","modified":1701429515599,"created":1701425762259,"url":"{{ _.host }}/login","name":"Login","description":"","method":"GET","body":{"mimeType":"application/json","text":"{\n\t\"email\": \"email123@email.com\",\n\t\"senha\": \"!Vinicius123\"\n}"},"parameters":[],"headers":[{"name":"Content-Type","value":"application/json"},{"name":"User-Agent","value":"insomnia/8.4.5"}],"authentication":{},"metaSortKey":-1701425762259,"isPrivate":false,"settingStoreCookies":true,"settingSendCookies":true,"settingDisableRenderRequestBody":false,"settingEncodeUrl":true,"settingRebuildPath":true,"settingFollowRedirects":"global","_type":"request"},{"_id":"env_df6f80104ce8edb68659a65e7652237ee5c6efbd","parentId":"wrk_e703ff469f4642b2a84f934941732103","modified":1701428170618,"created":1701425758718,"name":"Base Environment","data":{"token":"Bearer eyJhbGciOiJIUzI1NiIsInR5cCI6IkpXVCJ9.eyJ1c3VhcmlvX2xvZ2Fkb19pZCI6MSwidXN1YXJpb19sb2dhZG9fbm9tZSI6IlZpbmljaXVzIiwiaWF0IjoxNzAxNDI4MTUzLCJleHAiOjE3MDE0MzE3NTN9.A_TF7seaAIfKoD2n3BCRSnx7l1FurHoSnIhben0SgAw","host":"http://localhost:3000"},"dataPropertyOrder":{"&":["token","host"]},"color":null,"isPrivate":false,"metaSortKey":1701425758718,"_type":"environment"},{"_id":"jar_df6f80104ce8edb68659a65e7652237ee5c6efbd","parentId":"wrk_e703ff469f4642b2a84f934941732103","modified":1701425758719,"created":1701425758719,"name":"Default Jar","cookies":[],"_type":"cookie_jar"}]}